smooth_rpc/__init__.py
smooth_rpc/exceptions.py
smooth_rpc/network.py
smooth_rpc/smoothrpc.py
smoothrpc-0.9.3.dist-info/LICENSE
smoothrpc-0.9.3.dist-info/METADATA
smoothrpc-0.9.3.dist-info/WHEEL
smoothrpc-0.9.3.dist-info/RECORD
