Metadata-Version: 2.1
Name: SmoothRPC
Version: 0.9.3
Summary: Decorator-based RPC library based on asyncio.
Keywords: asyncio,rpc
Author: weary
Author-email: wearyspam@weary.nl
Requires-Python: >=3.11,<4.0
Classifier: Programming Language :: Python :: 3
Classifier: Programming Language :: Python :: 3.11
Classifier: Programming Language :: Python :: 3.12
Classifier: Programming Language :: Python :: 3.13
